astro_gdt-2.2.2.data/scripts/gdt-data
astro_gdt-2.2.2.dist-info/licenses/license.txt
gdt/core/__init__.py
gdt/core/collection.py
gdt/core/data_primitives.py
gdt/core/detector.py
gdt/core/file.py
gdt/core/fits.py
gdt/core/geomagnetic.py
gdt/core/headers.py
gdt/core/healpix.py
gdt/core/heasarc.py
gdt/core/pha.py
gdt/core/phaii.py
gdt/core/response.py
gdt/core/time.py
gdt/core/trigger.py
gdt/core/tte.py
gdt/core/types.py
gdt/core/background/__init__.py
gdt/core/background/binned.py
gdt/core/background/fitter.py
gdt/core/background/primitives.py
gdt/core/background/unbinned.py
gdt/core/binning/__init__.py
gdt/core/binning/binned.py
gdt/core/binning/unbinned.py
gdt/core/coords/__init__.py
gdt/core/coords/quaternion.py
gdt/core/coords/spacecraft/__init__.py
gdt/core/coords/spacecraft/axes.py
gdt/core/coords/spacecraft/frame.py
gdt/core/coords/spacecraft/model.py
gdt/core/plot/__init__.py
gdt/core/plot/defaults.py
gdt/core/plot/drm.py
gdt/core/plot/earthplot.py
gdt/core/plot/lib.py
gdt/core/plot/lightcurve.py
gdt/core/plot/model.py
gdt/core/plot/plot.py
gdt/core/plot/sky.py
gdt/core/plot/spectrum.py
gdt/core/simulate/__init__.py
gdt/core/simulate/generators.py
gdt/core/simulate/pha.py
gdt/core/simulate/profiles.py
gdt/core/simulate/tte.py
gdt/core/spectra/__init__.py
gdt/core/spectra/fitting.py
gdt/core/spectra/functions.py
gdt/core/spectra/parameters.py
gdt/core/temporal/__init__.py
gdt/core/temporal/duration.py
gdt/data/specfit.npz
gdt/misc/__init__.py
gdt/misc/scipy_derivative.py
astro_gdt-2.2.2.dist-info/METADATA
astro_gdt-2.2.2.dist-info/WHEEL
astro_gdt-2.2.2.dist-info/top_level.txt
astro_gdt-2.2.2.dist-info/RECORD
