Metadata-Version: 2.4
Name: astro-gdt
Version: 2.2.2
Summary: Gamma-ray Data Tools: Core Components
Author: William Cleveland, Adam Goldstein, Daniel Kocevski
Author-email: STI-Software@usra.edu
License-Expression: Apache-2.0
Project-URL: Documentation, https://astro-gdt.readthedocs.io/en/latest/
Project-URL: Repository, https://github.com/USRA-STI/gdt-core
Project-URL: Issues, https://github.com/USRA-STI/gdt-core/issues
Keywords: astronomy,gammaray,gamma-ray,usra
Classifier: Development Status :: 5 - Production/Stable
Classifier: Programming Language :: Python :: 3
Classifier: Programming Language :: Python :: 3.11
Classifier: Operating System :: MacOS
Classifier: Operating System :: POSIX :: Linux
Classifier: Topic :: Scientific/Engineering :: Astronomy
Classifier: Topic :: Software Development :: Libraries
Requires-Python: >=3.11
License-File: license.txt
Requires-Dist: pyproj>=1.9.6
Requires-Dist: numpy>=2.2.3
Requires-Dist: scipy==1.15.2
Requires-Dist: astropy>=7.0.0
Requires-Dist: matplotlib~=3.10.0
Requires-Dist: healpy~=1.18.0
Requires-Dist: cartopy>=0.21.1
Requires-Dist: rich>=13.3.3
Provides-Extra: test
Requires-Dist: pytest; extra == "test"
Provides-Extra: docs
Requires-Dist: Sphinx==5.0.2; extra == "docs"
Requires-Dist: astropy-sphinx-theme; extra == "docs"
Requires-Dist: nbsphinx; extra == "docs"
Requires-Dist: sphinx-automodapi; extra == "docs"
Dynamic: license-file
